README
setup.py
librarywatch/__init__.py
librarywatch/models.py
librarywatch/tests.py
librarywatch/views.py
librarywatch.egg-info/PKG-INFO
librarywatch.egg-info/SOURCES.txt
librarywatch.egg-info/dependency_links.txt
librarywatch.egg-info/top_level.txt
librarywatch/management/__init__.py
librarywatch/management/commands/__init__.py
librarywatch/management/commands/check_for_updates.py