Metadata-Version: 1.0
Name: librarywatch
Version: 1.0.1
Summary: A utility to check PyPi for updates to currently installed packages
Home-page: https://github.com/adamfast/django-librarywatch
Author: Jeff Triplett / Adam Fast
Author-email: adamfast@gmail.com
License: UNKNOWN
Platform: UNKNOWN
Classifier: Development Status :: 5 - Production/Stable
Classifier: Environment :: Web Environment
Classifier: Framework :: Django
Classifier: Intended Audience :: Developers
Classifier: License :: OSI Approved :: BSD License
Classifier: Operating System :: OS Independent
Classifier: Programming Language :: Python
Classifier: Topic :: Utilities
